redis/__init__.py
redis/_compat.py
redis/client.py
redis/connection.py
redis/exceptions.py
redis/lock.py
redis/sentinel.py
redis/utils.py
redispy-3.0.0.dist-info/DESCRIPTION.rst
redispy-3.0.0.dist-info/METADATA
redispy-3.0.0.dist-info/RECORD
redispy-3.0.0.dist-info/WHEEL
redispy-3.0.0.dist-info/metadata.json
redispy-3.0.0.dist-info/top_level.txt
