Metadata-Version: 1.1
Name: redispy
Version: 3.0.0
Summary: Python client for Redis key-value store
Home-page: http://github.com/jamiecressey/redispy
Author: Jamie Cressey
Author-email: jamiecressey89@gmail.com
License: MIT
Keywords: Redis,key-value store
Platform: UNKNOWN
Classifier: Development Status :: 5 - Production/Stable
Classifier: Environment :: Console
Classifier: Intended Audience :: Developers
Classifier: License :: OSI Approved :: MIT License
Classifier: Operating System :: OS Independent
Classifier: Programming Language :: Python
Classifier: Programming Language :: Python :: 2.6
Classifier: Programming Language :: Python :: 2.7
Classifier: Programming Language :: Python :: 3
Classifier: Programming Language :: Python :: 3.3
Classifier: Programming Language :: Python :: 3.4
Classifier: Programming Language :: Python :: 3.5
